mycalc/calculator.py
subeen_mycalc-0.0.1.dist-info/METADATA
subeen_mycalc-0.0.1.dist-info/WHEEL
subeen_mycalc-0.0.1.dist-info/top_level.txt
subeen_mycalc-0.0.1.dist-info/RECORD
