Metadata-Version: 2.1
Name: subeen-mycalc
Version: 0.0.1
Summary: nice calculator
Home-page: https://github.com/psb0/calculator
Download-URL: https://github.com/psb0/calculator
Author: psd0
License: UNKNOWN
Platform: UNKNOWN
Classifier: Programming Language :: Python :: 3
